<annotation><folder>original</folder><filename>dir1_fovs1_fovs1_frame2.jpg_out14-54.jpg</filename><source><url>dlaas-prd-207/AnnotationDataset/20200508173155-animal-data/dir1_fovs1_fovs1_frame2.jpg_out14.png</url></source><size><width>1920</width><height>1208</height><depth>3</depth></size><segmented>0</segmented><object><name>cat</name><pose>Unspecified</pose><truncated>0</truncated><difficult>0</difficult><bndbox><xmin>203</xmin><ymin>450</ymin><xmax>303</xmax><ymax>499</ymax></bndbox></object><object><name>dog</name><pose>Unspecified</pose><truncated>0</truncated><difficult>0</difficult><bndbox><xmin>1592</xmin><ymin>944</ymin><xmax>1709</xmax><ymax>1118</ymax></bndbox></object><object><name>car</name><pose>Unspecified</pose><truncated>0</truncated><difficult>0</difficult><bndbox><xmin>1399</xmin><ymin>697</ymin><xmax>1559</xmax><ymax>758</ymax></bndbox></object><object><name>bus</name><pose>Unspecified</pose><truncated>0</truncated><difficult>0</difficult><bndbox><xmin>1834</xmin><ymin>397</ymin><xmax>1920</xmax><ymax>489</ymax></bndbox></object></annotation>