<annotation><folder>original</folder><filename>dir12_8cam_910_6_fovs1_fovs1_frame236.jpg_out16-1850.jpg</filename><source><url>dlaas-prd-207/AnnotationDataset/20200508173155-animal-data/dir12_8cam_910_6_fovs1_fovs1_frame236.jpg_out16.png</url></source><size><width>1920</width><height>1208</height><depth>3</depth></size><segmented>0</segmented><object><name>car</name><pose>Unspecified</pose><truncated>0</truncated><difficult>0</difficult><bndbox><xmin>1340</xmin><ymin>584</ymin><xmax>1715</xmax><ymax>825</ymax></bndbox></object><object><name>car</name><pose>Unspecified</pose><truncated>0</truncated><difficult>0</difficult><bndbox><xmin>1094</xmin><ymin>567</ymin><xmax>1236</xmax><ymax>681</ymax></bndbox></object><object><name>car</name><pose>Unspecified</pose><truncated>0</truncated><difficult>0</difficult><bndbox><xmin>899</xmin><ymin>582</ymin><xmax>1068</xmax><ymax>720</ymax></bndbox></object><object><name>car</name><pose>Unspecified</pose><truncated>0</truncated><difficult>0</difficult><bndbox><xmin>568</xmin><ymin>575</ymin><xmax>759</xmax><ymax>718</ymax></bndbox></object><object><name>car</name><pose>Unspecified</pose><truncated>0</truncated><difficult>0</difficult><bndbox><xmin>93</xmin><ymin>536</ymin><xmax>581</xmax><ymax>884</ymax></bndbox></object><object><name>car</name><pose>Unspecified</pose><truncated>0</truncated><difficult>0</difficult><bndbox><xmin>85</xmin><ymin>533</ymin><xmax>418</xmax><ymax>765</ymax></bndbox></object><object><name>car</name><pose>Unspecified</pose><truncated>0</truncated><difficult>0</difficult><bndbox><xmin>531</xmin><ymin>584</ymin><xmax>590</xmax><ymax>624</ymax></bndbox></object><object><name>truck</name><pose>Unspecified</pose><truncated>0</truncated><difficult>0</difficult><bndbox><xmin>575</xmin><ymin>534</ymin><xmax>663</xmax><ymax>615</ymax></bndbox></object><object><name>prohibit</name><pose>Unspecified</pose><truncated>0</truncated><difficult>0</difficult><bndbox><xmin>1119</xmin><ymin>495</ymin><xmax>1133</xmax><ymax>510</ymax></bndbox></object><object><name>signal_lamp</name><pose>Unspecified</pose><truncated>0</truncated><difficult>0</difficult><bndbox><xmin>1252</xmin><ymin>407</ymin><xmax>1267</xmax><ymax>450</ymax></bndbox></object><object><name>signal_lamp</name><pose>Unspecified</pose><truncated>0</truncated><difficult>0</difficult><bndbox><xmin>1185</xmin><ymin>404</ymin><xmax>1201</xmax><ymax>447</ymax></bndbox></object><object><name>signal_lamp</name><pose>Unspecified</pose><truncated>0</truncated><difficult>0</difficult><bndbox><xmin>854</xmin><ymin>388</ymin><xmax>871</xmax><ymax>435</ymax></bndbox></object><object><name>signal_lamp</name><pose>Unspecified</pose><truncated>0</truncated><difficult>0</difficult><bndbox><xmin>789</xmin><ymin>396</ymin><xmax>806</xmax><ymax>441</ymax></bndbox></object><object><name>prohibit</name><pose>Unspecified</pose><truncated>0</truncated><difficult>0</difficult><bndbox><xmin>814</xmin><ymin>404</ymin><xmax>844</xmax><ymax>434</ymax></bndbox></object><object><name>cat</name><pose>Unspecified</pose><truncated>0</truncated><difficult>0</difficult><bndbox><xmin>981</xmin><ymin>651</ymin><xmax>1090</xmax><ymax>827</ymax></bndbox></object></annotation>