<annotation><folder>original</folder><filename>dir12_8cam_910_6_fovs1_fovs1_frame300.jpg_out1-737.jpg</filename><source><url>dlaas-prd-207/AnnotationDataset/20200508173155-animal-data/dir12_8cam_910_6_fovs1_fovs1_frame300.jpg_out1.png</url></source><size><width>1920</width><height>1208</height><depth>3</depth></size><segmented>0</segmented><object><name>prohibit</name><pose>Unspecified</pose><truncated>0</truncated><difficult>0</difficult><bndbox><xmin>1081</xmin><ymin>377</ymin><xmax>1116</xmax><ymax>412</ymax></bndbox></object><object><name>prohibit</name><pose>Unspecified</pose><truncated>0</truncated><difficult>0</difficult><bndbox><xmin>1197</xmin><ymin>500</ymin><xmax>1211</xmax><ymax>515</ymax></bndbox></object><object><name>truck</name><pose>Unspecified</pose><truncated>0</truncated><difficult>0</difficult><bndbox><xmin>1232</xmin><ymin>315</ymin><xmax>1720</xmax><ymax>719</ymax></bndbox></object><object><name>truck</name><pose>Unspecified</pose><truncated>0</truncated><difficult>0</difficult><bndbox><xmin>1118</xmin><ymin>535</ymin><xmax>1202</xmax><ymax>617</ymax></bndbox></object><object><name>truck</name><pose>Unspecified</pose><truncated>0</truncated><difficult>0</difficult><bndbox><xmin>887</xmin><ymin>552</ymin><xmax>915</xmax><ymax>587</ymax></bndbox></object><object><name>car</name><pose>Unspecified</pose><truncated>0</truncated><difficult>0</difficult><bndbox><xmin>1041</xmin><ymin>559</ymin><xmax>1135</xmax><ymax>641</ymax></bndbox></object><object><name>car</name><pose>Unspecified</pose><truncated>0</truncated><difficult>0</difficult><bndbox><xmin>1004</xmin><ymin>562</ymin><xmax>1029</xmax><ymax>594</ymax></bndbox></object><object><name>truck</name><pose>Unspecified</pose><truncated>0</truncated><difficult>0</difficult><bndbox><xmin>1083</xmin><ymin>544</ymin><xmax>1120</xmax><ymax>582</ymax></bndbox></object><object><name>car</name><pose>Unspecified</pose><truncated>0</truncated><difficult>0</difficult><bndbox><xmin>858</xmin><ymin>573</ymin><xmax>877</xmax><ymax>589</ymax></bndbox></object><object><name>car</name><pose>Unspecified</pose><truncated>0</truncated><difficult>0</difficult><bndbox><xmin>914</xmin><ymin>572</ymin><xmax>930</xmax><ymax>586</ymax></bndbox></object><object><name>car</name><pose>Unspecified</pose><truncated>0</truncated><difficult>0</difficult><bndbox><xmin>438</xmin><ymin>586</ymin><xmax>509</xmax><ymax>623</ymax></bndbox></object><object><name>car</name><pose>Unspecified</pose><truncated>0</truncated><difficult>0</difficult><bndbox><xmin>657</xmin><ymin>579</ymin><xmax>697</xmax><ymax>604</ymax></bndbox></object><object><name>cyclist</name><pose>Unspecified</pose><truncated>0</truncated><difficult>0</difficult><bndbox><xmin>432</xmin><ymin>586</ymin><xmax>451</xmax><ymax>616</ymax></bndbox></object><object><name>cyclist</name><pose>Unspecified</pose><truncated>0</truncated><difficult>0</difficult><bndbox><xmin>632</xmin><ymin>580</ymin><xmax>644</xmax><ymax>601</ymax></bndbox></object><object><name>cat</name><pose>Unspecified</pose><truncated>0</truncated><difficult>0</difficult><bndbox><xmin>818</xmin><ymin>710</ymin><xmax>1068</xmax><ymax>811</ymax></bndbox></object><object><name>truck</name><pose>Unspecified</pose><truncated>0</truncated><difficult>0</difficult><bndbox><xmin>1041</xmin><ymin>563</ymin><xmax>1065</xmax><ymax>585</ymax></bndbox></object><object><name>truck</name><pose>Unspecified</pose><truncated>0</truncated><difficult>0</difficult><bndbox><xmin>995</xmin><ymin>570</ymin><xmax>1011</xmax><ymax>584</ymax></bndbox></object><object><name>signal_lamp</name><pose>Unspecified</pose><truncated>0</truncated><difficult>0</difficult><bndbox><xmin>1051</xmin><ymin>382</ymin><xmax>1069</xmax><ymax>433</ymax></bndbox></object><object><name>signal_lamp</name><pose>Unspecified</pose><truncated>0</truncated><difficult>0</difficult><bndbox><xmin>1129</xmin><ymin>378</ymin><xmax>1145</xmax><ymax>428</ymax></bndbox></object></annotation>