<annotation><folder>original</folder><filename>dir12_8cam_910_6_fovs1_fovs1_frame334.jpg_out4-5172.jpg</filename><source><url>dlaas-prd-207/AnnotationDataset/20200508173155-animal-data/dir12_8cam_910_6_fovs1_fovs1_frame334.jpg_out4.png</url></source><size><width>1920</width><height>1208</height><depth>3</depth></size><segmented>0</segmented><object><name>dog</name><pose>Unspecified</pose><truncated>0</truncated><difficult>0</difficult><bndbox><xmin>1462</xmin><ymin>940</ymin><xmax>1593</xmax><ymax>1073</ymax></bndbox></object><object><name>dog</name><pose>Unspecified</pose><truncated>0</truncated><difficult>0</difficult><bndbox><xmin>1570</xmin><ymin>965</ymin><xmax>1699</xmax><ymax>1043</ymax></bndbox></object><object><name>cat</name><pose>Unspecified</pose><truncated>0</truncated><difficult>0</difficult><bndbox><xmin>527</xmin><ymin>510</ymin><xmax>585</xmax><ymax>601</ymax></bndbox></object><object><name>truck</name><pose>Unspecified</pose><truncated>0</truncated><difficult>0</difficult><bndbox><xmin>806</xmin><ymin>553</ymin><xmax>837</xmax><ymax>576</ymax></bndbox></object><object><name>truck</name><pose>Unspecified</pose><truncated>0</truncated><difficult>0</difficult><bndbox><xmin>995</xmin><ymin>553</ymin><xmax>1010</xmax><ymax>574</ymax></bndbox></object><object><name>car</name><pose>Unspecified</pose><truncated>0</truncated><difficult>0</difficult><bndbox><xmin>993</xmin><ymin>563</ymin><xmax>1008</xmax><ymax>575</ymax></bndbox></object><object><name>car</name><pose>Unspecified</pose><truncated>0</truncated><difficult>0</difficult><bndbox><xmin>1023</xmin><ymin>564</ymin><xmax>1033</xmax><ymax>574</ymax></bndbox></object><object><name>car</name><pose>Unspecified</pose><truncated>0</truncated><difficult>0</difficult><bndbox><xmin>1029</xmin><ymin>562</ymin><xmax>1039</xmax><ymax>574</ymax></bndbox></object><object><name>car</name><pose>Unspecified</pose><truncated>0</truncated><difficult>0</difficult><bndbox><xmin>1010</xmin><ymin>564</ymin><xmax>1018</xmax><ymax>574</ymax></bndbox></object><object><name>prohibit</name><pose>Unspecified</pose><truncated>0</truncated><difficult>0</difficult><bndbox><xmin>1359</xmin><ymin>406</ymin><xmax>1389</xmax><ymax>432</ymax></bndbox></object></annotation>