<annotation><folder>original</folder><filename>dir12_8cam_910_6_fovs1_fovs1_frame209.jpg_out7-1193.jpg</filename><source><url>dlaas-prd-207/AnnotationDataset/20200508173155-animal-data/dir12_8cam_910_6_fovs1_fovs1_frame209.jpg_out7.png</url></source><size><width>1920</width><height>1208</height><depth>3</depth></size><segmented>0</segmented><object><name>cat</name><pose>Unspecified</pose><truncated>0</truncated><difficult>0</difficult><bndbox><xmin>774</xmin><ymin>636</ymin><xmax>859</xmax><ymax>808</ymax></bndbox></object><object><name>car</name><pose>Unspecified</pose><truncated>0</truncated><difficult>0</difficult><bndbox><xmin>1467</xmin><ymin>550</ymin><xmax>1635</xmax><ymax>658</ymax></bndbox></object><object><name>truck</name><pose>Unspecified</pose><truncated>0</truncated><difficult>0</difficult><bndbox><xmin>1117</xmin><ymin>549</ymin><xmax>1201</xmax><ymax>608</ymax></bndbox></object><object><name>car</name><pose>Unspecified</pose><truncated>0</truncated><difficult>0</difficult><bndbox><xmin>753</xmin><ymin>572</ymin><xmax>858</xmax><ymax>647</ymax></bndbox></object><object><name>truck</name><pose>Unspecified</pose><truncated>0</truncated><difficult>0</difficult><bndbox><xmin>812</xmin><ymin>553</ymin><xmax>864</xmax><ymax>597</ymax></bndbox></object><object><name>car</name><pose>Unspecified</pose><truncated>0</truncated><difficult>0</difficult><bndbox><xmin>166</xmin><ymin>553</ymin><xmax>252</xmax><ymax>606</ymax></bndbox></object><object><name>car</name><pose>Unspecified</pose><truncated>0</truncated><difficult>0</difficult><bndbox><xmin>521</xmin><ymin>562</ymin><xmax>564</xmax><ymax>596</ymax></bndbox></object><object><name>car</name><pose>Unspecified</pose><truncated>0</truncated><difficult>0</difficult><bndbox><xmin>701</xmin><ymin>555</ymin><xmax>720</xmax><ymax>571</ymax></bndbox></object><object><name>car</name><pose>Unspecified</pose><truncated>0</truncated><difficult>0</difficult><bndbox><xmin>658</xmin><ymin>560</ymin><xmax>683</xmax><ymax>582</ymax></bndbox></object><object><name>car</name><pose>Unspecified</pose><truncated>0</truncated><difficult>0</difficult><bndbox><xmin>781</xmin><ymin>550</ymin><xmax>797</xmax><ymax>564</ymax></bndbox></object><object><name>car</name><pose>Unspecified</pose><truncated>0</truncated><difficult>0</difficult><bndbox><xmin>764</xmin><ymin>550</ymin><xmax>779</xmax><ymax>563</ymax></bndbox></object><object><name>car</name><pose>Unspecified</pose><truncated>0</truncated><difficult>0</difficult><bndbox><xmin>627</xmin><ymin>560</ymin><xmax>652</xmax><ymax>576</ymax></bndbox></object><object><name>truck</name><pose>Unspecified</pose><truncated>0</truncated><difficult>0</difficult><bndbox><xmin>592</xmin><ymin>538</ymin><xmax>615</xmax><ymax>558</ymax></bndbox></object><object><name>car</name><pose>Unspecified</pose><truncated>0</truncated><difficult>0</difficult><bndbox><xmin>898</xmin><ymin>562</ymin><xmax>944</xmax><ymax>604</ymax></bndbox></object></annotation>