<annotation><folder>original</folder><filename>dir12_8cam_910_6_fovs1_fovs1_frame123.jpg_out5-1710.jpg</filename><source><url>dlaas-prd-207/AnnotationDataset/20200508173155-animal-data/dir12_8cam_910_6_fovs1_fovs1_frame123.jpg_out5.png</url></source><size><width>1920</width><height>1208</height><depth>3</depth></size><segmented>0</segmented><object><name>cat</name><pose>Unspecified</pose><truncated>0</truncated><difficult>0</difficult><bndbox><xmin>1176</xmin><ymin>709</ymin><xmax>1259</xmax><ymax>850</ymax></bndbox></object><object><name>car</name><pose>Unspecified</pose><truncated>0</truncated><difficult>0</difficult><bndbox><xmin>1655</xmin><ymin>587</ymin><xmax>1920</xmax><ymax>1122</ymax></bndbox></object><object><name>car</name><pose>Unspecified</pose><truncated>0</truncated><difficult>0</difficult><bndbox><xmin>1327</xmin><ymin>552</ymin><xmax>1689</xmax><ymax>788</ymax></bndbox></object><object><name>car</name><pose>Unspecified</pose><truncated>0</truncated><difficult>0</difficult><bndbox><xmin>1184</xmin><ymin>558</ymin><xmax>1366</xmax><ymax>690</ymax></bndbox></object><object><name>truck</name><pose>Unspecified</pose><truncated>0</truncated><difficult>0</difficult><bndbox><xmin>855</xmin><ymin>480</ymin><xmax>1163</xmax><ymax>761</ymax></bndbox></object><object><name>car</name><pose>Unspecified</pose><truncated>0</truncated><difficult>0</difficult><bndbox><xmin>1120</xmin><ymin>545</ymin><xmax>1229</xmax><ymax>646</ymax></bndbox></object><object><name>person</name><pose>Unspecified</pose><truncated>0</truncated><difficult>0</difficult><bndbox><xmin>820</xmin><ymin>555</ymin><xmax>853</xmax><ymax>625</ymax></bndbox></object><object><name>car</name><pose>Unspecified</pose><truncated>0</truncated><difficult>0</difficult><bndbox><xmin>516</xmin><ymin>547</ymin><xmax>641</xmax><ymax>631</ymax></bndbox></object><object><name>car</name><pose>Unspecified</pose><truncated>0</truncated><difficult>0</difficult><bndbox><xmin>626</xmin><ymin>562</ymin><xmax>668</xmax><ymax>597</ymax></bndbox></object><object><name>signal_lamp</name><pose>Unspecified</pose><truncated>0</truncated><difficult>0</difficult><bndbox><xmin>966</xmin><ymin>411</ymin><xmax>977</xmax><ymax>446</ymax></bndbox></object><object><name>signal_lamp</name><pose>Unspecified</pose><truncated>0</truncated><difficult>0</difficult><bndbox><xmin>1031</xmin><ymin>409</ymin><xmax>1043</xmax><ymax>440</ymax></bndbox></object><object><name>prohibit</name><pose>Unspecified</pose><truncated>0</truncated><difficult>0</difficult><bndbox><xmin>992</xmin><ymin>416</ymin><xmax>1016</xmax><ymax>438</ymax></bndbox></object><object><name>signal_lamp</name><pose>Unspecified</pose><truncated>0</truncated><difficult>0</difficult><bndbox><xmin>1186</xmin><ymin>434</ymin><xmax>1196</xmax><ymax>463</ymax></bndbox></object><object><name>signal_lamp</name><pose>Unspecified</pose><truncated>0</truncated><difficult>0</difficult><bndbox><xmin>1241</xmin><ymin>436</ymin><xmax>1251</xmax><ymax>465</ymax></bndbox></object><object><name>signal_lamp</name><pose>Unspecified</pose><truncated>0</truncated><difficult>0</difficult><bndbox><xmin>800</xmin><ymin>239</ymin><xmax>824</xmax><ymax>313</ymax></bndbox></object><object><name>signal_lamp</name><pose>Unspecified</pose><truncated>0</truncated><difficult>0</difficult><bndbox><xmin>929</xmin><ymin>226</ymin><xmax>959</xmax><ymax>299</ymax></bndbox></object><object><name>signal_lamp</name><pose>Unspecified</pose><truncated>0</truncated><difficult>0</difficult><bndbox><xmin>1524</xmin><ymin>277</ymin><xmax>1550</xmax><ymax>343</ymax></bndbox></object><object><name>signal_lamp</name><pose>Unspecified</pose><truncated>0</truncated><difficult>0</difficult><bndbox><xmin>1642</xmin><ymin>280</ymin><xmax>1669</xmax><ymax>348</ymax></bndbox></object><object><name>dog</name><pose>Unspecified</pose><truncated>0</truncated><difficult>0</difficult><bndbox><xmin>1313</xmin><ymin>545</ymin><xmax>1427</xmax><ymax>641</ymax></bndbox></object></annotation>