<annotation><folder>original</folder><filename>dir12_8cam_910_6_fovs1_fovs1_frame75.jpg_out16-3305.jpg</filename><source><url>dlaas-prd-207/AnnotationDataset/20200508173155-animal-data/dir12_8cam_910_6_fovs1_fovs1_frame75.jpg_out16.png</url></source><size><width>1920</width><height>1208</height><depth>3</depth></size><segmented>0</segmented><object><name>dog</name><pose>Unspecified</pose><truncated>0</truncated><difficult>0</difficult><bndbox><xmin>906</xmin><ymin>704</ymin><xmax>966</xmax><ymax>775</ymax></bndbox></object><object><name>cat</name><pose>Unspecified</pose><truncated>0</truncated><difficult>0</difficult><bndbox><xmin>208</xmin><ymin>443</ymin><xmax>301</xmax><ymax>509</ymax></bndbox></object><object><name>car</name><pose>Unspecified</pose><truncated>0</truncated><difficult>0</difficult><bndbox><xmin>1002</xmin><ymin>562</ymin><xmax>1032</xmax><ymax>587</ymax></bndbox></object><object><name>car</name><pose>Unspecified</pose><truncated>0</truncated><difficult>0</difficult><bndbox><xmin>940</xmin><ymin>561</ymin><xmax>980</xmax><ymax>593</ymax></bndbox></object><object><name>car</name><pose>Unspecified</pose><truncated>0</truncated><difficult>0</difficult><bndbox><xmin>1068</xmin><ymin>562</ymin><xmax>1112</xmax><ymax>597</ymax></bndbox></object><object><name>car</name><pose>Unspecified</pose><truncated>0</truncated><difficult>0</difficult><bndbox><xmin>1059</xmin><ymin>562</ymin><xmax>1088</xmax><ymax>588</ymax></bndbox></object><object><name>car</name><pose>Unspecified</pose><truncated>0</truncated><difficult>0</difficult><bndbox><xmin>1052</xmin><ymin>559</ymin><xmax>1079</xmax><ymax>584</ymax></bndbox></object><object><name>car</name><pose>Unspecified</pose><truncated>0</truncated><difficult>0</difficult><bndbox><xmin>1042</xmin><ymin>561</ymin><xmax>1066</xmax><ymax>583</ymax></bndbox></object><object><name>truck</name><pose>Unspecified</pose><truncated>0</truncated><difficult>0</difficult><bndbox><xmin>953</xmin><ymin>553</ymin><xmax>988</xmax><ymax>588</ymax></bndbox></object><object><name>signal_lamp</name><pose>Unspecified</pose><truncated>0</truncated><difficult>0</difficult><bndbox><xmin>1094</xmin><ymin>492</ymin><xmax>1105</xmax><ymax>514</ymax></bndbox></object><object><name>signal_lamp</name><pose>Unspecified</pose><truncated>0</truncated><difficult>0</difficult><bndbox><xmin>1121</xmin><ymin>492</ymin><xmax>1131</xmax><ymax>514</ymax></bndbox></object><object><name>signal_lamp</name><pose>Unspecified</pose><truncated>0</truncated><difficult>0</difficult><bndbox><xmin>1064</xmin><ymin>509</ymin><xmax>1071</xmax><ymax>527</ymax></bndbox></object></annotation>