<annotation><folder>original</folder><filename>dir12_8cam_910_6_fovs1_fovs1_frame217.jpg_out16-1694.jpg</filename><source><url>dlaas-prd-207/AnnotationDataset/20200508173155-animal-data/dir12_8cam_910_6_fovs1_fovs1_frame217.jpg_out16.png</url></source><size><width>1920</width><height>1208</height><depth>3</depth></size><segmented>0</segmented><object><name>cyclist</name><pose>Unspecified</pose><truncated>0</truncated><difficult>0</difficult><bndbox><xmin>1452</xmin><ymin>555</ymin><xmax>1474</xmax><ymax>626</ymax></bndbox></object><object><name>truck</name><pose>Unspecified</pose><truncated>0</truncated><difficult>0</difficult><bndbox><xmin>724</xmin><ymin>522</ymin><xmax>864</xmax><ymax>649</ymax></bndbox></object><object><name>truck</name><pose>Unspecified</pose><truncated>0</truncated><difficult>0</difficult><bndbox><xmin>509</xmin><ymin>539</ymin><xmax>620</xmax><ymax>592</ymax></bndbox></object><object><name>car</name><pose>Unspecified</pose><truncated>0</truncated><difficult>0</difficult><bndbox><xmin>956</xmin><ymin>559</ymin><xmax>1022</xmax><ymax>615</ymax></bndbox></object><object><name>car</name><pose>Unspecified</pose><truncated>0</truncated><difficult>0</difficult><bndbox><xmin>946</xmin><ymin>548</ymin><xmax>968</xmax><ymax>570</ymax></bndbox></object><object><name>car</name><pose>Unspecified</pose><truncated>0</truncated><difficult>0</difficult><bndbox><xmin>1032</xmin><ymin>552</ymin><xmax>1058</xmax><ymax>570</ymax></bndbox></object><object><name>car</name><pose>Unspecified</pose><truncated>0</truncated><difficult>0</difficult><bndbox><xmin>994</xmin><ymin>547</ymin><xmax>1015</xmax><ymax>565</ymax></bndbox></object><object><name>car</name><pose>Unspecified</pose><truncated>0</truncated><difficult>0</difficult><bndbox><xmin>975</xmin><ymin>544</ymin><xmax>988</xmax><ymax>557</ymax></bndbox></object><object><name>car</name><pose>Unspecified</pose><truncated>0</truncated><difficult>0</difficult><bndbox><xmin>1016</xmin><ymin>542</ymin><xmax>1031</xmax><ymax>554</ymax></bndbox></object><object><name>cat</name><pose>Unspecified</pose><truncated>0</truncated><difficult>0</difficult><bndbox><xmin>1436</xmin><ymin>768</ymin><xmax>1634</xmax><ymax>1033</ymax></bndbox></object></annotation>