<annotation><folder>original</folder><filename>dir8_fovs1_fovs1_frame9.jpg_out13-2309.jpg</filename><source><url>dlaas-prd-207/AnnotationDataset/20200508173155-animal-data/dir8_fovs1_fovs1_frame9.jpg_out13.png</url></source><size><width>1920</width><height>1208</height><depth>3</depth></size><segmented>0</segmented><object><name>dog</name><pose>Unspecified</pose><truncated>0</truncated><difficult>0</difficult><bndbox><xmin>1102</xmin><ymin>773</ymin><xmax>1197</xmax><ymax>885</ymax></bndbox></object><object><name>cat</name><pose>Unspecified</pose><truncated>0</truncated><difficult>0</difficult><bndbox><xmin>203</xmin><ymin>433</ymin><xmax>258</xmax><ymax>520</ymax></bndbox></object><object><name>car</name><pose>Unspecified</pose><truncated>0</truncated><difficult>0</difficult><bndbox><xmin>163</xmin><ymin>697</ymin><xmax>255</xmax><ymax>747</ymax></bndbox></object><object><name>barricade </name><pose>Unspecified</pose><truncated>0</truncated><difficult>0</difficult><bndbox><xmin>399</xmin><ymin>720</ymin><xmax>422</xmax><ymax>737</ymax></bndbox></object><object><name>barricade </name><pose>Unspecified</pose><truncated>0</truncated><difficult>0</difficult><bndbox><xmin>427</xmin><ymin>721</ymin><xmax>457</xmax><ymax>739</ymax></bndbox></object><object><name>barricade </name><pose>Unspecified</pose><truncated>0</truncated><difficult>0</difficult><bndbox><xmin>481</xmin><ymin>722</ymin><xmax>505</xmax><ymax>739</ymax></bndbox></object><object><name>barricade </name><pose>Unspecified</pose><truncated>0</truncated><difficult>0</difficult><bndbox><xmin>526</xmin><ymin>722</ymin><xmax>554</xmax><ymax>740</ymax></bndbox></object><object><name>barricade </name><pose>Unspecified</pose><truncated>0</truncated><difficult>0</difficult><bndbox><xmin>567</xmin><ymin>716</ymin><xmax>584</xmax><ymax>731</ymax></bndbox></object><object><name>barricade </name><pose>Unspecified</pose><truncated>0</truncated><difficult>0</difficult><bndbox><xmin>578</xmin><ymin>720</ymin><xmax>601</xmax><ymax>736</ymax></bndbox></object><object><name>barricade </name><pose>Unspecified</pose><truncated>0</truncated><difficult>0</difficult><bndbox><xmin>601</xmin><ymin>716</ymin><xmax>620</xmax><ymax>729</ymax></bndbox></object><object><name>barricade </name><pose>Unspecified</pose><truncated>0</truncated><difficult>0</difficult><bndbox><xmin>625</xmin><ymin>718</ymin><xmax>646</xmax><ymax>735</ymax></bndbox></object><object><name>barricade </name><pose>Unspecified</pose><truncated>0</truncated><difficult>0</difficult><bndbox><xmin>646</xmin><ymin>715</ymin><xmax>658</xmax><ymax>726</ymax></bndbox></object><object><name>barricade </name><pose>Unspecified</pose><truncated>0</truncated><difficult>0</difficult><bndbox><xmin>661</xmin><ymin>718</ymin><xmax>680</xmax><ymax>733</ymax></bndbox></object><object><name>barricade </name><pose>Unspecified</pose><truncated>0</truncated><difficult>0</difficult><bndbox><xmin>690</xmin><ymin>718</ymin><xmax>713</xmax><ymax>732</ymax></bndbox></object><object><name>barricade </name><pose>Unspecified</pose><truncated>0</truncated><difficult>0</difficult><bndbox><xmin>684</xmin><ymin>716</ymin><xmax>699</xmax><ymax>727</ymax></bndbox></object></annotation>