<annotation><folder>original</folder><filename>fovs1_frame20.jpg_out19-4903.jpg</filename><source><url>dlaas-prd-207/AnnotationDataset/20200508173155-animal-data/fovs1_frame20.jpg_out19.png</url></source><size><width>1920</width><height>1208</height><depth>3</depth></size><segmented>0</segmented><object><name>car</name><pose>Unspecified</pose><truncated>0</truncated><difficult>0</difficult><bndbox><xmin>847</xmin><ymin>559</ymin><xmax>879</xmax><ymax>584</ymax></bndbox></object><object><name>truck</name><pose>Unspecified</pose><truncated>0</truncated><difficult>0</difficult><bndbox><xmin>909</xmin><ymin>540</ymin><xmax>963</xmax><ymax>602</ymax></bndbox></object><object><name>person</name><pose>Unspecified</pose><truncated>0</truncated><difficult>0</difficult><bndbox><xmin>1458</xmin><ymin>562</ymin><xmax>1481</xmax><ymax>628</ymax></bndbox></object><object><name>person</name><pose>Unspecified</pose><truncated>0</truncated><difficult>0</difficult><bndbox><xmin>1601</xmin><ymin>563</ymin><xmax>1628</xmax><ymax>626</ymax></bndbox></object><object><name>dog</name><pose>Unspecified</pose><truncated>0</truncated><difficult>0</difficult><bndbox><xmin>968</xmin><ymin>720</ymin><xmax>1058</xmax><ymax>809</ymax></bndbox></object><object><name>car</name><pose>Unspecified</pose><truncated>0</truncated><difficult>0</difficult><bndbox><xmin>343</xmin><ymin>557</ymin><xmax>579</xmax><ymax>652</ymax></bndbox></object><object><name>cat</name><pose>Unspecified</pose><truncated>0</truncated><difficult>0</difficult><bndbox><xmin>199</xmin><ymin>444</ymin><xmax>301</xmax><ymax>527</ymax></bndbox></object><object><name>car</name><pose>Unspecified</pose><truncated>0</truncated><difficult>0</difficult><bndbox><xmin>117</xmin><ymin>551</ymin><xmax>251</xmax><ymax>629</ymax></bndbox></object><object><name>signal_lamp</name><pose>Unspecified</pose><truncated>0</truncated><difficult>0</difficult><bndbox><xmin>881</xmin><ymin>358</ymin><xmax>899</xmax><ymax>407</ymax></bndbox></object><object><name>signal_lamp</name><pose>Unspecified</pose><truncated>0</truncated><difficult>0</difficult><bndbox><xmin>1249</xmin><ymin>348</ymin><xmax>1269</xmax><ymax>402</ymax></bndbox></object><object><name>prohibit</name><pose>Unspecified</pose><truncated>0</truncated><difficult>0</difficult><bndbox><xmin>828</xmin><ymin>368</ymin><xmax>861</xmax><ymax>402</ymax></bndbox></object></annotation>