<annotation><folder>original</folder><filename>fovs1_frame2.jpg_out18-5691.jpg</filename><source><url>dlaas-prd-207/AnnotationDataset/20200508173155-animal-data/fovs1_frame2.jpg_out18.png</url></source><size><width>1920</width><height>1208</height><depth>3</depth></size><segmented>0</segmented><object><name>cat</name><pose>Unspecified</pose><truncated>0</truncated><difficult>0</difficult><bndbox><xmin>1144</xmin><ymin>701</ymin><xmax>1225</xmax><ymax>838</ymax></bndbox></object><object><name>cyclist</name><pose>Unspecified</pose><truncated>0</truncated><difficult>0</difficult><bndbox><xmin>1369</xmin><ymin>546</ymin><xmax>1403</xmax><ymax>635</ymax></bndbox></object><object><name>bus</name><pose>Unspecified</pose><truncated>0</truncated><difficult>0</difficult><bndbox><xmin>1447</xmin><ymin>505</ymin><xmax>1618</xmax><ymax>620</ymax></bndbox></object><object><name>car</name><pose>Unspecified</pose><truncated>0</truncated><difficult>0</difficult><bndbox><xmin>1747</xmin><ymin>554</ymin><xmax>1848</xmax><ymax>612</ymax></bndbox></object><object><name>cyclist</name><pose>Unspecified</pose><truncated>0</truncated><difficult>0</difficult><bndbox><xmin>1197</xmin><ymin>561</ymin><xmax>1215</xmax><ymax>600</ymax></bndbox></object><object><name>cyclist</name><pose>Unspecified</pose><truncated>0</truncated><difficult>0</difficult><bndbox><xmin>1120</xmin><ymin>564</ymin><xmax>1133</xmax><ymax>595</ymax></bndbox></object><object><name>cyclist</name><pose>Unspecified</pose><truncated>0</truncated><difficult>0</difficult><bndbox><xmin>1141</xmin><ymin>564</ymin><xmax>1154</xmax><ymax>590</ymax></bndbox></object><object><name>car</name><pose>Unspecified</pose><truncated>0</truncated><difficult>0</difficult><bndbox><xmin>900</xmin><ymin>557</ymin><xmax>1063</xmax><ymax>689</ymax></bndbox></object><object><name>car</name><pose>Unspecified</pose><truncated>0</truncated><difficult>0</difficult><bndbox><xmin>907</xmin><ymin>564</ymin><xmax>962</xmax><ymax>610</ymax></bndbox></object><object><name>truck</name><pose>Unspecified</pose><truncated>0</truncated><difficult>0</difficult><bndbox><xmin>845</xmin><ymin>551</ymin><xmax>889</xmax><ymax>597</ymax></bndbox></object><object><name>cyclist</name><pose>Unspecified</pose><truncated>0</truncated><difficult>0</difficult><bndbox><xmin>1169</xmin><ymin>561</ymin><xmax>1181</xmax><ymax>589</ymax></bndbox></object><object><name>car</name><pose>Unspecified</pose><truncated>0</truncated><difficult>0</difficult><bndbox><xmin>676</xmin><ymin>569</ymin><xmax>714</xmax><ymax>598</ymax></bndbox></object><object><name>truck</name><pose>Unspecified</pose><truncated>0</truncated><difficult>0</difficult><bndbox><xmin>288</xmin><ymin>506</ymin><xmax>449</xmax><ymax>630</ymax></bndbox></object><object><name>signal_lamp</name><pose>Unspecified</pose><truncated>0</truncated><difficult>0</difficult><bndbox><xmin>809</xmin><ymin>377</ymin><xmax>824</xmax><ymax>421</ymax></bndbox></object><object><name>signal_lamp</name><pose>Unspecified</pose><truncated>0</truncated><difficult>0</difficult><bndbox><xmin>901</xmin><ymin>370</ymin><xmax>918</xmax><ymax>415</ymax></bndbox></object><object><name>prohibit</name><pose>Unspecified</pose><truncated>0</truncated><difficult>0</difficult><bndbox><xmin>853</xmin><ymin>382</ymin><xmax>881</xmax><ymax>410</ymax></bndbox></object><object><name>signal_lamp</name><pose>Unspecified</pose><truncated>0</truncated><difficult>0</difficult><bndbox><xmin>1101</xmin><ymin>405</ymin><xmax>1116</xmax><ymax>444</ymax></bndbox></object><object><name>signal_lamp</name><pose>Unspecified</pose><truncated>0</truncated><difficult>0</difficult><bndbox><xmin>1181</xmin><ymin>409</ymin><xmax>1196</xmax><ymax>446</ymax></bndbox></object><object><name>signal_lamp</name><pose>Unspecified</pose><truncated>0</truncated><difficult>0</difficult><bndbox><xmin>1667</xmin><ymin>0</ymin><xmax>1723</xmax><ymax>79</ymax></bndbox></object><object><name>signal_lamp</name><pose>Unspecified</pose><truncated>0</truncated><difficult>0</difficult><bndbox><xmin>275</xmin><ymin>0</ymin><xmax>339</xmax><ymax>42</ymax></bndbox></object><object><name>person</name><pose>Unspecified</pose><truncated>0</truncated><difficult>0</difficult><bndbox><xmin>1755</xmin><ymin>538</ymin><xmax>1768</xmax><ymax>589</ymax></bndbox></object></annotation>